lektor_netlify_lfs_resize_url.py
lektor_netlify_lfs_resize_url-1.0.3.dist-info/LICENSE
lektor_netlify_lfs_resize_url-1.0.3.dist-info/METADATA
lektor_netlify_lfs_resize_url-1.0.3.dist-info/WHEEL
lektor_netlify_lfs_resize_url-1.0.3.dist-info/entry_points.txt
lektor_netlify_lfs_resize_url-1.0.3.dist-info/top_level.txt
lektor_netlify_lfs_resize_url-1.0.3.dist-info/RECORD
