Metadata-Version: 2.1
Name: lektor-netlify-lfs-resize-url
Version: 1.0.3
Summary: Convert image URLs to Netlify LFS resize URLs.
Home-page: https://gitlab.com/JM0804/lektor-netlify-lfs-resize-url
Author: Jonathan Mason
License: MIT
Keywords: Lektor plugin
Classifier: Framework :: Lektor
Classifier: Environment :: Plugins
License-File: LICENSE
